Metadata-Version: 2.1
Name: somerandomstuff.py
Version: 0.1.3
Summary: A module to get info from somerandomstuff api
Home-page: https://github.com/Sengolda/somerandomstuffpy
Author: Sengolda
License: MIT
Platform: UNKNOWN
